{
  "hash": "7a61bb97",
  "configHash": "74343f7d",
  "lockfileHash": "1f7c34c2",
  "browserHash": "b2b436cc",
  "optimized": {
    "react": {
      "src": "../../node_modules/react/index.js",
      "file": "react.js",
      "fileHash": "085edb76",
      "needsInterop": true
    },
    "react-dom/client": {
      "src": "../../node_modules/react-dom/client.js",
      "file": "react-dom_client.js",
      "fileHash": "cc9e5990",
      "needsInterop": true
    },
    "react-router-dom": {
      "src": "../../node_modules/react-router-dom/dist/index.mjs",
      "file": "react-router-dom.js",
      "fileHash": "de11fc8b",
      "needsInterop": false
    },
    "lenis": {
      "src": "../../node_modules/lenis/dist/lenis.mjs",
      "file": "lenis.js",
      "fileHash": "97cabee7",
      "needsInterop": false
    },
    "framer-motion": {
      "src": "../../node_modules/framer-motion/dist/es/index.mjs",
      "file": "framer-motion.js",
      "fileHash": "08c88cec",
      "needsInterop": false
    },
    "lucide-react": {
      "src": "../../node_modules/lucide-react/dist/esm/lucide-react.js",
      "file": "lucide-react.js",
      "fileHash": "0e2c586a",
      "needsInterop": false
    },
    "gsap": {
      "src": "../../node_modules/gsap/index.js",
      "file": "gsap.js",
      "fileHash": "01bdc214",
      "needsInterop": false
    }
  },
  "chunks": {
    "chunk-UP6LQVYV": {
      "file": "chunk-UP6LQVYV.js"
    },
    "chunk-TWJRYSII": {
      "file": "chunk-TWJRYSII.js"
    },
    "chunk-DC5AMYBS": {
      "file": "chunk-DC5AMYBS.js"
    }
  }
}